{
  "meta": {
    "stableOrder": true
  },
  "lockfileVersion": 3,
  "ATTENTION": "THIS IS AN AUTOGENERATED FILE. DO NOT EDIT THIS FILE DIRECTLY.",
  "specifiers": {
    "@ohos/md360player@../vrlib": "@ohos/md360player@../vrlib",
    "libmd360player.so@../vrlib/src/main/cpp/types/libmd360player": "libmd360player.so@../vrlib/src/main/cpp/types/libmd360player"
  },
  "packages": {
    "@ohos/md360player@../vrlib": {
      "name": "@ohos/md360player",
      "version": "1.0.0-rc.0",
      "resolved": "../vrlib",
      "registryType": "local",
      "dependencies": {
        "libmd360player.so": "file:./src/main/cpp/types/libmd360player"
      }
    },
    "libmd360player.so@../vrlib/src/main/cpp/types/libmd360player": {
      "name": "libmd360player.so",
      "version": "1.0.0",
      "resolved": "../vrlib/src/main/cpp/types/libmd360player",
      "registryType": "local"
    }
  }
}